odoo9_addon_hr_family-9.0.1.0.0-py2.7-nspkg.pth
odoo_addons/hr_family/__openerp__.py
odoo_addons/hr_family/__init__.py
odoo_addons/hr_family/README.rst
odoo_addons/hr_family/security/ir.model.access.csv
odoo_addons/hr_family/models/hr_employee.py
odoo_addons/hr_family/models/hr_children.py
odoo_addons/hr_family/models/__init__.py
odoo_addons/hr_family/i18n/zh_CN.po
odoo_addons/hr_family/i18n/pt.po
odoo_addons/hr_family/i18n/it.po
odoo_addons/hr_family/i18n/es.po
odoo_addons/hr_family/i18n/ar.po
odoo_addons/hr_family/i18n/ro.po
odoo_addons/hr_family/i18n/tr.po
odoo_addons/hr_family/i18n/hr.po
odoo_addons/hr_family/i18n/bg.po
odoo_addons/hr_family/i18n/gl.po
odoo_addons/hr_family/i18n/ca.po
odoo_addons/hr_family/i18n/sl.po
odoo_addons/hr_family/i18n/es_ES.po
odoo_addons/hr_family/i18n/pt_PT.po
odoo_addons/hr_family/i18n/nl.po
odoo_addons/hr_family/i18n/am.po
odoo_addons/hr_family/i18n/de.po
odoo_addons/hr_family/i18n/fr.po
odoo_addons/hr_family/i18n/pl.po
odoo_addons/hr_family/i18n/pt_BR.po
odoo_addons/hr_family/i18n/el_GR.po
odoo_addons/hr_family/i18n/fi.po
odoo_addons/hr_family/i18n/hr_HR.po
odoo_addons/hr_family/views/hr_employee.xml
odoo_addons/hr_family/views/hr_children.xml
odoo_addons/hr_family/static/description/icon.png
odoo9_addon_hr_family-9.0.1.0.0.dist-info/top_level.txt
odoo9_addon_hr_family-9.0.1.0.0.dist-info/WHEEL
odoo9_addon_hr_family-9.0.1.0.0.dist-info/RECORD
odoo9_addon_hr_family-9.0.1.0.0.dist-info/metadata.json
odoo9_addon_hr_family-9.0.1.0.0.dist-info/DESCRIPTION.rst
odoo9_addon_hr_family-9.0.1.0.0.dist-info/METADATA
odoo9_addon_hr_family-9.0.1.0.0.dist-info/namespace_packages.txt
